Workbook

Sheet Sheet 1
A1: Sr. No. | B1: Particulars | C1: Input Value | D1: Units | E1: Remark
A2: 1 | B2: Solar Generation Capacity | C2: 4499.83 | D2: kWp | E2: Client input
A3: 2 | B3: Solar Generation Capacity | C3: 3300 | D3: kW | E3: Client input
A4: 3 | B4: Solar Supplied unit at Generation Bus Bar | C4: =G25 -> 237415
A5: 3.b | B5: Less: Wheeling Loss (7.50%) | C5: =C4*0.075 -> 17806.125
A6: 3.c | B6: Less: State Transmission Loss (3.28%) | C6: =(C4-C5)*3.28% -> 7203.1711
A7: 3.d | B7: Quantum at buyers periphery | C7: =C4-C5-C6 -> 212405.7
A8: 4.a | B8: Add: Wheeling Charge (0.74) | C8: =G25*0.81 -> 192306.15
A9: 4.b | B9: Add: State Transmission Charge (0.8771) | C9: 242163.3 | E9: From Bill pdf
A10: 4.c | B10: Add: Operating Charge | C10: =IF(C3<5000,16500,29830) -> 16500
A11: 5 | B11: Total Charges | C11: =SUM(C8:C10) -> 450969.45
A12: 1 | B12: Consumption Details
A13: a | B13: Month | E13: From Bill pdf
A14: b | B14: Contract Demand (kVA) | C14: 1800 | E14: From Bill pdf
A15: c | B15: Energy Charges (₹/kVAh) | C15: 8.44 | E15: From Bill pdf
A16: d | B16: Demand Charges (₹/kVA) | C16: 650 | E16: From Bill pdf
A17: e | B17: Wheeling Charges (₹/kVAh) | C17: 0.81 | E17: From Bill pdf
A18: f | B18: FAC (₹/kVAh) | C18: 0.5 | E18: From Bill pdf
A19: g | B19: Tax on Sales (₹/kVAh) | C19: 0.2894 | E19: From Bill pdf
A20: h | B20: Power Factor | C20: 1 | E20: From Bill pdf
A21: i | B21: Maximum Demand (kVA) | C21: 1488 | E21: From Bill pdf
A22: j | B22: Electricity Duty | C22: 0.075 | D22: 8.44 | E22: =7.17-C15 -> -1.27 | F22: =10.55-C15 -> 2.11 | K22: Reference for TOD calculation of Solar Generation
C23: Zone A | D23: Zone B | E23: Zone C | F23: Zone D | G23: Total | K23: Zone A | L23: Zone B | M23: Zone C | N23: Zone D | O23: Total
A24: k | B24: Consumption Before Solar | C24: =SUM(C25:C26) -> 166499 | D24: =SUM(D25:D26) -> 71263.75 | E24: =SUM(E25:E26) -> 215033.75 | F24: =SUM(F25:F26) -> 210750.5 | G24: =SUM(G25:G26) -> 663547 | J24: TOD Charges | K24: =K26+K25 -> 166499 | L24: =L26+L25 -> 71263.75 | M24: =M26+M25 -> 215033.75 | N24: =N26+N25 -> 210750.5 | O24: =SUM(K24:N24) -> 663547
A25: l | B25: Solar Units at consumption end | C25: =K25/C20 -> 0 | D25: =L25/C20 -> 11870.75 | E25: =M25/C20 -> 201802.75 | F25: =N25/C20 -> 23741.5 | G25: =SUM(C25:F25) -> 237415 | H25: 237415 | I25: From bill pdf | J25: TOD SOLAR Generation metre | K25: =H25*K28 -> 0 | L25: =H25*L28 -> 11870.75 | M25: =H25*M28 -> 201802.75 | N25: =H25*N28 -> 23741.5 | O25: =SUM(K25:N25) -> 237415
A26: m | B26: Billed Consumption after Solar | C26: =K26/C20 -> 166499 | D26: =L26/C20 -> 59393 | E26: =M26/C20 -> 13231 | F26: =N26/C20 -> 187009 | G26: =SUM(C26:F26) -> 426132 | K26: 166499 | L26: 59393 | M26: 13231 | N26: 187009 | O26: =SUM(K26:N26) -> 426132
A27: n | B27: TOD Rate | C27: 0 | D27: 0 | E27: -1.27 | F27: 2.11 | K27: 0 | L27: 0 | M27: -2.17 | N27: 2.17
B28: Load Factor | C28: =ROUND(G24*100/C14/24/DAY(EOMONTH(C13,0)),0) -> 50 | D28: =ROUND(G26*100/C14/24/DAY(EOMONTH(C13,0)),0) -> 32 | K28: 0 | L28: 0.05 | M28: 0.85 | N28: 0.1
B29: Load Factor Incentive | C29: =IF(C28>75,IF(C28>85,IF(C28>92,14.5%,(((C28-85)*1%)+((85-75)*0.75%))),((C28-75)*0.75%)),0) -> 0 | D29: =IF(D28>75,IF(D28>85,IF(D28>92,14.5%,(((D28-85)*1%)+((85-75)*0.75%))),((D28-75)*0.75%)),0) -> 0
B30: Billed Demand | C30: 1488 | E30: From Bill pdf
B31: Bulk Consumption Slab
B32: (100000-1000000 kWh) | C32: =IF(G$24<100000,0,IF(G$24>1000000,(1000000-100000),(G$24-100000))) -> 563547 | D32: =IF(G$26<100000,0,IF(G$26>1000000,(1000000-100000),(G$26-100000))) -> 326132
B33: (1000000 kWh - 5000000 kWh) | C33: =IF(G$24<1000000,0,IF(G$24>5000000,(5000000-1000000),(G$24-1000000))) -> 0 | D33: =IF(G$26<1000000,0,IF(G$26>5000000,(5000000-1000000),(G$26-1000000))) -> 0
B34: (5000000 kWh +) | C34: =IF(G$24<5000000,0,(G$24-5000000)) -> 0 | D34: =IF(G$26<5000000,0,(G$26-5000000)) -> 0
B35: Bulk Consumption Rebate
B36: (100000-1000000 kWh) | C36: 0.07
B37: (1000000 kWh - 5000000 kWh) | C37: 0.09
B38: (5000000 kWh +) | C38: 0.11
B39: Incremental Consumption Rebate
B40: Reference Units | C40: 564383 | E40: From Bill pdf

Sheet Output -Bill After Solar_Apr 26
A1: Sr. No. | B1: Particulars | C1: Before Solar | D1: After Solar - Captive
A2: 1 | B2: Consumption Details
A3: a | B3: Base month | C3: 46113 | D3: =C3 -> 46113
A4: b | B4: Source 1 - MSEDCL | C4: ='Sheet 1'!G24 -> 663547 | D4: ='Sheet 1'!G26 -> 426132
A5: c | B5: Source 2 - Solar Power Plant | C5: 0 | D5: ='Sheet 1'!G25 -> 237415
A6: d | B6: Total Consumption | C6: =C4+C5 -> 663547 | D6: =D4+D5 -> 663547
A8: 2 | B8: Computation of Electricity Bill based on consumption in Apr-26
A9: A | B9: Bill for MSEDCL Consumption
A10: i | B10: Demand Charges | C10: ='Sheet 1'!$C$30*'Sheet 1'!$C$16 -> 967200 | D10: ='Sheet 1'!$C$30*'Sheet 1'!$C$16 -> 967200
A11: ii | B11: Wheeling Charges | C11: ='Sheet 1'!$G$24*'Sheet 1'!$C$17 -> 537473.07 | D11: ='Sheet 1'!$G$26*'Sheet 1'!$C$17 -> 345166.92
A12: iii | B12: Energy Charges | C12: ='Sheet 1'!$G$24*'Sheet 1'!$C$15 -> 5600336.7 | D12: ='Sheet 1'!$G$26*'Sheet 1'!$C$15 -> 3596554.1
A13: iv | B13: TOD Tariff Energy Charges | C13: {=SUMPRODUCT('Sheet 1'!$C$24:$F$24,'Sheet 1'!$C$27:$F$27)} -> 171590.69 | D13: {=SUMPRODUCT('Sheet 1'!$C$26:$F$26,'Sheet 1'!$C$27:$F$27)} -> 377785.62
A14: v | B14: FAC | C14: ='Sheet 1'!$G$24*'Sheet 1'!$C$18 -> 331773.5 | D14: ='Sheet 1'!$G$26*'Sheet 1'!$C$18 -> 213066
A15: vi | B15: Electricity Duty | C15: =(SUM(C10:C14)+C20)*'Sheet 1'!$C$22 -> 570628.05 | D15: =(SUM(D10:D14)+D20)*'Sheet 1'!$C$22 -> 412482.95
A16: vii | B16: Bulk Consumption Rebate | C16: {=-SUMPRODUCT('Sheet 1'!C32:C34,'Sheet 1'!$C$36:$C$38)} -> -39448.29 | D16: {=-SUMPRODUCT('Sheet 1'!D32:D34,'Sheet 1'!$C$36:$C$38)} -> -22829.24
A17: viii | B17: Tax on Sale | C17: ='Sheet 1'!$C$19*'Sheet 1'!$C$20*'Sheet 1'!$G$24 -> 192030.5 | D17: ='Sheet 1'!$C$19*'Sheet 1'!$C$20*'Sheet 1'!$G$26 -> 123322.6
A18: ix | B18: Load Factor Incentive | C18: 0 | D18: 0
A19: x | B19: Incremental Consumption Rebate | C19: =IF(((C4-'Sheet 1'!C40)*-0.75*'Sheet 1'!C20)>0,0,((C4-'Sheet 1'!C40)*-0.75*'Sheet 1'!C20)) -> -74373 | D19: =IF(((D4-'Sheet 1'!C40)*-0.75*'Sheet 1'!C20)>0,0,((D4-'Sheet 1'!C40)*-0.75*'Sheet 1'!C20)) -> 0
A20: xi | B20: Charges for Excess Demand | C20: =D20 -> 0 | D20: =IF('Sheet 1'!D21>'Sheet 1'!C14,(('Sheet 1'!D21-'Sheet 1'!C14)*1.5*'Sheet 1'!D16),0) -> 0
A21: xii | B21: Tax Collection at Source | C21: 0 | D21: 0
A22: xiii | B22: Debit Bill adjustment | C22: 0 | D22: 609816.75
A23: xiv | B23: Total Bill for MSEDCL Consumption | C23: =SUM(C10:C22) -> 8257211.2 | D23: =SUM(D10:D22) -> 6622565.7
A24: B | B24: Bill for Open Access
B25: Tax on Sale | D25: ='Sheet 1'!C19*'Sheet 1'!C20*'Sheet 1'!G25 -> 68707.901
A26: i | B26: Wheeling Charges | C26: 0 | D26: ='Sheet 1'!C8 -> 192306.15
A27: ii | B27: Transmission Charges | C27: 0 | D27: ='Sheet 1'!C9 -> 242163.3
A28: iii | B28: Operating Charges | C28: 0 | D28: ='Sheet 1'!C10 -> 16500
A29: iv | B29: Total Bill for Open Access | C29: =SUM(C26:C28) -> 0 | D29: =SUM(D25:D28) -> 519677.35
A30: C | B30: Total MSEDCL Bill | C30: =C29+C23 -> 8257211.2 | D30: =D29+D23 -> 7142243
A31: D | B31: O&M Cost per month | C31: 0
A32: D | B32: Total Cost of power | C32: =C31+C30 -> 8257211.2 | D32: =D31+D30 -> 7142243
A33: F | B33: Net Savings | D33: =$C$32-D32 -> 1114968.2
A34: D | B34: Average Cost of Power | C34: =C32/C6 -> 12.444049 | D34: =D32/D6 -> 10.763733
A35: E | B35: Total Savings | D35: =C30-D30 -> 1114968.2
A36: F | B36: % Savings | D36: =D35/C32 -> 0.13502963
